oauth2_proxy_cookie.py
oauth2_proxy_cookie_256-0.1.1.dist-info/LICENSE
oauth2_proxy_cookie_256-0.1.1.dist-info/METADATA
oauth2_proxy_cookie_256-0.1.1.dist-info/WHEEL
oauth2_proxy_cookie_256-0.1.1.dist-info/top_level.txt
oauth2_proxy_cookie_256-0.1.1.dist-info/RECORD
